README.md
setup.py
ilens_kafka_publisher/__init__.py
ilens_kafka_publisher.egg-info/PKG-INFO
ilens_kafka_publisher.egg-info/SOURCES.txt
ilens_kafka_publisher.egg-info/dependency_links.txt
ilens_kafka_publisher.egg-info/top_level.txt
ilens_kafka_publisher/v2/__init__.py