Metadata-Version: 2.1
Name: ilens-kafka-publisher
Version: 0.4.2.1
Summary: Utility for Publishing messages to Kafka in iLens
Home-page: https://unifytwin.com
Author: Charan
Author-email: charankumar@knowledgelens.com
License: Restricted
Platform: UNKNOWN
